typecount/__init__.py
typecount/app.py
typecount-0.2.0.dist-info/licenses/LICENSE
typecount-0.2.0.dist-info/METADATA
typecount-0.2.0.dist-info/WHEEL
typecount-0.2.0.dist-info/entry_points.txt
typecount-0.2.0.dist-info/top_level.txt
typecount-0.2.0.dist-info/RECORD
