Metadata-Version: 2.4
Name: typecount
Version: 0.2.0
Summary: A simple typing counter application
Requires-Python: >=3.12
License-File: LICENSE
Requires-Dist: pynput>=1.7.7
Dynamic: license-file
